botoolkit/__init__.py
botoolkit/settings.py
botoolkit/bo_barsdock/__init__.py
botoolkit/bo_barsdock/commands.py
botoolkit/bo_barsdock/enums.py
botoolkit/bo_barsdock/main.py
botoolkit/bo_barsdock/mixins.py
botoolkit/bo_barsdock/settings.py
botoolkit/bo_barsdock/templates/__init__.py
botoolkit/bo_barsdock/templates/bobarsdock.conf
botoolkit/bo_conf/__init__.py
botoolkit/bo_conf/api.py
botoolkit/bo_conf/commands.py
botoolkit/bo_conf/consts.py
botoolkit/bo_conf/enums.py
botoolkit/bo_conf/helpers.py
botoolkit/bo_conf/main.py
botoolkit/bo_conf/mixins.py
botoolkit/bo_conf/settings.py
botoolkit/bo_conf/strings.py
botoolkit/bo_conf/templates/__init__.py
botoolkit/bo_conf/templates/boconf.conf
botoolkit/bo_databaser/__init__.py
botoolkit/bo_databaser/commands.py
botoolkit/bo_databaser/consts.py
botoolkit/bo_databaser/main.py
botoolkit/bo_databaser/mixins.py
botoolkit/bo_databaser/services.py
botoolkit/bo_databaser/settings.py
botoolkit/bo_databaser/templates/__init__.py
botoolkit/bo_databaser/templates/bodatabaser.conf
botoolkit/bo_databaser/templates/bodatabaser_build.conf
botoolkit/bo_git/__init__.py
botoolkit/bo_git/commands.py
botoolkit/bo_git/enums.py
botoolkit/bo_git/helpers.py
botoolkit/bo_git/main.py
botoolkit/bo_git/mixins.py
botoolkit/bo_git/settings.py
botoolkit/bo_git/strings.py
botoolkit/bo_git/templates/__init__.py
botoolkit/bo_git/templates/bogit.conf
botoolkit/bo_guide/__init__.py
botoolkit/bo_guide/commands.py
botoolkit/bo_guide/consts.py
botoolkit/bo_guide/main.py
botoolkit/bo_guide/mixins.py
botoolkit/bo_guide/settings.py
botoolkit/bo_guide/templates/__init__.py
botoolkit/bo_guide/templates/boguide.conf
botoolkit/bo_ip/__init__.py
botoolkit/bo_ip/api.py
botoolkit/bo_ip/commands.py
botoolkit/bo_ip/enums.py
botoolkit/bo_ip/helpers.py
botoolkit/bo_ip/main.py
botoolkit/bo_ip/settings.py
botoolkit/bo_ip/strings.py
botoolkit/bo_jenkins/__init__.py
botoolkit/bo_jenkins/commands.py
botoolkit/bo_jenkins/consts.py
botoolkit/bo_jenkins/enums.py
botoolkit-1.2.5.dist-info/METADATA
botoolkit-1.2.5.dist-info/WHEEL
botoolkit-1.2.5.dist-info/entry_points.txt
botoolkit-1.2.5.dist-info/namespace_packages.txt
botoolkit-1.2.5.dist-info/top_level.txt
botoolkit-1.2.5.dist-info/RECORD
