Metadata-Version: 2.1
Name: botoolkit
Version: 1.2.5
Summary: BO toolkit
Home-page: 
Download-URL: 
Author: Alexander Danilenko
Author-email: a.danilenko@bars.group
Platform: Any
Classifier: Development Status :: 3 - Alpha
Classifier: License :: OSI Approved :: Apache Software License
Classifier: Programming Language :: Python
Classifier: Programming Language :: Python :: 3
Classifier: Programming Language :: Python :: 3.9
Classifier: Intended Audience :: Developers
Classifier: Environment :: Console
Requires-Dist: ConfigUpdater ==3.0.1
Requires-Dist: GitPython ==3.1.24
Requires-Dist: PyYAML ==6.0
Requires-Dist: cliff ==3.9.0
Requires-Dist: docker ==5.0.3
Requires-Dist: fabric ==2.6.0
Requires-Dist: jira ==3.0.1
Requires-Dist: nexus3-cli ==4.1.5
Requires-Dist: psycopg2 ==2.9.2
Requires-Dist: pyOpenSSL ==21.0.0
Requires-Dist: pyparsing ==2.4.7
Requires-Dist: python-jenkins ==1.7.0
Requires-Dist: simplejson ==3.17.5
Requires-Dist: uvloop ==0.16.0
Requires-Dist: validators ==0.18.2
